waveresponse/__init__.py
waveresponse/_core.py
waveresponse/_standardized1d.py
waveresponse/_transform.py
waveresponse/_utils.py
waveresponse-1.4.1.dist-info/licenses/LICENSE
waveresponse-1.4.1.dist-info/METADATA
waveresponse-1.4.1.dist-info/WHEEL
waveresponse-1.4.1.dist-info/top_level.txt
waveresponse-1.4.1.dist-info/RECORD
