Metadata-Version: 2.4
Name: waveresponse
Version: 1.4.1
Summary: Vessel motion and wave utilities
Author-email: 4Subsea <python@4subsea.com>
License: MIT License
Project-URL: Homepage, https://github.com/4Subsea/waveresponse-python
Project-URL: Bug Tracker, https://github.com/4Subsea/waveresponse-python/issues
Project-URL: Documentation, https://docs.4insight.io/waveresponse/python/latest/
Classifier: Programming Language :: Python :: 3.9
Classifier: Programming Language :: Python :: 3.10
Classifier: Programming Language :: Python :: 3.11
Classifier: License :: OSI Approved :: MIT License
Classifier: Operating System :: Unix
Classifier: Operating System :: Microsoft :: Windows
Requires-Python: >=3.9
License-File: LICENSE
Requires-Dist: numpy
Requires-Dist: pandas
Requires-Dist: scipy
Requires-Dist: pyarrow
Dynamic: license-file
